es_knowledge_base_mcp/.gitignore
es_knowledge_base_mcp/__init__.py
es_knowledge_base_mcp/clients/__init__.py
es_knowledge_base_mcp/clients/crawl.py
es_knowledge_base_mcp/clients/docker.py
es_knowledge_base_mcp/clients/es_knowledge_base.py
es_knowledge_base_mcp/clients/web.py
es_knowledge_base_mcp/errors/__init__.py
es_knowledge_base_mcp/errors/ask.py
es_knowledge_base_mcp/errors/crawler.py
es_knowledge_base_mcp/errors/fetch.py
es_knowledge_base_mcp/errors/knowledge_base.py
es_knowledge_base_mcp/errors/learn.py
es_knowledge_base_mcp/errors/server.py
es_knowledge_base_mcp/interfaces/__init__.py
es_knowledge_base_mcp/interfaces/knowledge_base.py
es_knowledge_base_mcp/models/__init__.py
es_knowledge_base_mcp/models/base.py
es_knowledge_base_mcp/models/constants.py
es_knowledge_base_mcp/models/settings.py
es_knowledge_base_mcp/server.py
es_knowledge_base_mcp/servers/__init__.py
es_knowledge_base_mcp/servers/ask.py
es_knowledge_base_mcp/servers/learn.py
es_knowledge_base_mcp/servers/manage.py
es_knowledge_base_mcp/servers/remember.py
es_knowledge_base_mcp-0.1.0.dist-info/METADATA
es_knowledge_base_mcp-0.1.0.dist-info/WHEEL
es_knowledge_base_mcp-0.1.0.dist-info/entry_points.txt
es_knowledge_base_mcp-0.1.0.dist-info/RECORD
