Metadata-Version: 2.3
Name: es-knowledge-base-mcp
Version: 0.1.0
Summary: An MCP server for crawling documentation, writing it to Elasticsearch for vector search retrieval by an LLM.
Author: Bill Easton
Author-email: williamseaston@gmail.com
Requires-Python: >=3.12,<3.13
Classifier: Programming Language :: Python :: 3
Classifier: Programming Language :: Python :: 3.12
Provides-Extra: dev
Requires-Dist: aiodocker (>=0.24.0)
Requires-Dist: aiohttp (>=3.11.14)
Requires-Dist: anyio (>=4.9.0,<5.0.0)
Requires-Dist: async-lru (>=2.0.5,<3.0.0)
Requires-Dist: asyncio (>=3.4.3,<4.0.0)
Requires-Dist: beautifulsoup4 (>=4.12.3,<5.0.0)
Requires-Dist: elasticsearch (>=8.17.2,<9.0.0)
Requires-Dist: fastmcp (>=2.1.2)
Requires-Dist: markdownify (>=1.1.0,<2.0.0)
Requires-Dist: pydantic (>=2.0.0,<3.0.0)
Requires-Dist: pydantic-settings (>=2.3.4,<3.0.0)
Requires-Dist: pytest (>=8.3,<9.0.0) ; extra == "dev"
Requires-Dist: pytest-asyncio (>=0.26,<0.27.0) ; extra == "dev"
Requires-Dist: pyyaml (>=6.0.2,<7.0.0)
Requires-Dist: requests (>=2.32.3,<3.0.0)
Requires-Dist: requests-mock (>=1.12,<2.0.0) ; extra == "dev"
Requires-Dist: ruff (>=0.11) ; extra == "dev"
Requires-Dist: syrupy (>=4.9) ; extra == "dev"
